<?xml version="1.0" encoding="windows-1251" ?>
<game_dialogs>

<!--********************************-->
<!-- Sidorovich Miniquest dialog start -->
<!--********************************-->
    <dialog id="escape_trader_miniquest">
        <precondition>escape_dialog.trader_miniquest_precond</precondition>
        <has_info>tutorial_end</has_info> 
        <phrase_list>
            <phrase id="0">
                <text>escape_trader_miniquest_0</text>
                <next>1</next>
            </phrase>
            <phrase id="1">
                <text>escape_trader_miniquest_1</text>
                <next>2</next>
            </phrase>
            <phrase id="2">
                <text>escape_trader_miniquest_2</text>
                <next>3</next>
                <next>21</next>
            </phrase>
            <phrase id="3">
                <precondition>escape_dialog.trader_check_miniquest_free_neg</precondition>
                <text>escape_trader_miniquest_3</text>
                <next>4</next>
                <next>5</next>
                <next>6</next>
                <next>7</next>
            </phrase>
            <phrase id="4">
                <precondition>escape_dialog.trader_check_money_miniquest</precondition>
                <text>escape_trader_miniquest_5</text>
                <next>8</next>
            </phrase>
            <phrase id="5">
                <precondition>escape_dialog.trader_check_money_miniquest</precondition>
                <text>escape_trader_miniquest_6</text>
                <next>8</next>
            </phrase>
            <phrase id="6">
                <precondition>escape_dialog.trader_check_miniquest_free_all_neg</precondition>
                <text>escape_trader_miniquest_7</text>
                <next>10</next>
            </phrase>
            <phrase id="7">
                <text>escape_trader_miniquest_4</text>
            </phrase>
            <phrase id="8">
                <text>escape_trader_miniquest_8</text>
                <action>escape_dialog.trader_miniquest_transfer</action>
                <next>9</next>				
            </phrase>
            <phrase id="9">
                <text>escape_trader_miniquest_19</text>
            </phrase>
            <phrase id="10">
                <precondition>escape_dialog.trader_check_miniquest_free_neg</precondition>
                <text>escape_trader_miniquest_9</text>
                <next>11</next>
                <next>12</next>
                <next>13</next>
                <next>14</next>
            </phrase>
            <phrase id="11">
                <text>escape_trader_miniquest_10</text>
                <next>16</next>
            </phrase>
            <phrase id="12">
                <text>escape_trader_miniquest_11</text>
                <next>17</next>
            </phrase>
            <phrase id="13">
                <text>escape_trader_miniquest_12</text>
                <give_info>esc_trader_miniquest_free</give_info>
                <next>15</next>
            </phrase>
            <phrase id="14">
                <text>escape_trader_miniquest_13</text>
                <next>18</next>
            </phrase>
            <phrase id="15">
                <text>escape_trader_miniquest_16</text>
                <next>2</next>
            </phrase>
            <phrase id="16">
                <text>escape_trader_miniquest_14</text>
                <give_info>esc_trader_miniquest_notfree</give_info>				
                <next>19</next>
            </phrase>
            <phrase id="17">
                <text>escape_trader_miniquest_15</text>
                <give_info>esc_trader_miniquest_notfree</give_info>				
                <next>19</next>
            </phrase>
            <phrase id="18">
                <text>escape_trader_miniquest_17</text>
                <give_info>esc_trader_miniquest_notfree</give_info>				
                <next>19</next>
            </phrase>
            <phrase id="19">
                <text>escape_trader_miniquest_20</text>
                <next>20</next>
            </phrase>
            <phrase id="20">
                <text>escape_trader_miniquest_18</text>
                <next>4</next>
                <next>5</next>
                <next>7</next>
            </phrase>
            <phrase id="21">
                <precondition>escape_dialog.trader_check_miniquest_free</precondition>
                <text>escape_trader_miniquest_8</text>
                <action>escape_dialog.trader_miniquest_free_transfer</action>
                <next>9</next>
            </phrase>

		</phrase_list>
    </dialog>

<!--********************************-->
<!-- Barman Miniquest dialog start -->
<!--********************************-->
    <dialog id="bar_trader_miniquest">
        <precondition>bar_dialogs.trader_miniquest_precond</precondition>
        <has_info>tutorial_end</has_info>
        <phrase_list>
            <phrase id="0">
                <text>bar_trader_miniquest_0</text>
                <next>1</next>
            </phrase>
            <phrase id="1">
                <text>bar_trader_miniquest_1</text>
                <next>2</next>
            </phrase>
            <phrase id="2">
                <text>bar_trader_miniquest_2</text>
                <next>3</next>
            </phrase>
            <phrase id="3">
                <text>bar_trader_miniquest_3</text>
                <action>bar_dialogs.trader_miniquest_free_transfer</action>
                <next>4</next>
            </phrase>
            <phrase id="4">
                <text>bar_trader_miniquest_4</text>
            </phrase>
        </phrase_list>
    </dialog>
	
<!--********************-->
<!-- Miniquest dialogs end -->
<!--********************-->

</game_dialogs>
